billboardhotget/__init__.py
billboardhotget/billboard.py
billboardgetter-0.0.2.dist-info/METADATA
billboardgetter-0.0.2.dist-info/WHEEL
billboardgetter-0.0.2.dist-info/licenses/LICENSE
billboardgetter-0.0.2.dist-info/RECORD
