Metadata-Version: 2.3
Name: billboardgetter
Version: 0.0.2
Summary: A small web scraping package
Author-email: jyup <jyup.ect@gamil.com>
License: MIT License
Classifier: License :: OSI Approved :: MIT License
Classifier: Operating System :: OS Independent
Classifier: Programming Language :: Python :: 3
Requires-Python: >=3.7
Requires-Dist: bs4==0.0.1
Requires-Dist: requests>=2.28.2
